{
  "main": {
    "id": "ed55956c62ab2945",
    "type": "split",
    "children": [
      {
        "id": "042dc7c25b7c6272",
        "type": "tabs",
        "children": [
          {
            "id": "0047a872449aeab3",
            "type": "leaf",
            "state": {
              "type": "markdown",
              "state": {
                "file": "Statistics 110/독립 vs 조건부 독립.md",
                "mode": "source",
                "source": false
              }
            }
          },
          {
            "id": "cfa5d47192552f3d",
            "type": "leaf",
            "state": {
              "type": "markdown",
              "state": {
                "file": "Statistics 110/강의 인덱스.md",
                "mode": "source",
                "source": false
              }
            }
          },
          {
            "id": "a6df7858370d83a1",
            "type": "leaf",
            "state": {
              "type": "markdown",
              "state": {
                "file": "Statistics 110/연속 분포(Continuous Distribution).md",
                "mode": "source",
                "source": false
              }
            }
          }
        ]
      }
    ],
    "direction": "vertical"
  },
  "left": {
    "id": "f1e18cb9e99e1735",
    "type": "split",
    "children": [
      {
        "id": "679acc505724eee3",
        "type": "tabs",
        "children": [
          {
            "id": "c3b978f0a6ed0667",
            "type": "leaf",
            "state": {
              "type": "file-explorer",
              "state": {
                "sortOrder": "alphabetical"
              }
            }
          },
          {
            "id": "77431cc91228a397",
            "type": "leaf",
            "state": {
              "type": "search",
              "state": {
                "query": "Binom",
                "matchingCase": false,
                "explainSearch": false,
                "collapseAll": false,
                "extraContext": false,
                "sortOrder": "alphabetical"
              }
            }
          },
          {
            "id": "ae5fa329269aec37",
            "type": "leaf",
            "state": {
              "type": "bookmarks",
              "state": {}
            }
          }
        ]
      }
    ],
    "direction": "horizontal",
    "width": 300
  },
  "right": {
    "id": "6bf25aef3af8499f",
    "type": "split",
    "children": [
      {
        "id": "0d290ba3a52371b9",
        "type": "tabs",
        "children": [
          {
            "id": "c947d18249aea07c",
            "type": "leaf",
            "state": {
              "type": "backlink",
              "state": {
                "file": "Statistics 110/독립 vs 조건부 독립.md",
                "collapseAll": false,
                "extraContext": false,
                "sortOrder": "alphabetical",
                "showSearch": false,
                "searchQuery": "",
                "backlinkCollapsed": false,
                "unlinkedCollapsed": true
              }
            }
          },
          {
            "id": "44e84887b0b6439c",
            "type": "leaf",
            "state": {
              "type": "outgoing-link",
              "state": {
                "file": "Statistics 110/독립 vs 조건부 독립.md",
                "linksCollapsed": false,
                "unlinkedCollapsed": true
              }
            }
          },
          {
            "id": "e66ebc9560d08737",
            "type": "leaf",
            "state": {
              "type": "tag",
              "state": {
                "sortOrder": "frequency",
                "useHierarchy": true
              }
            }
          },
          {
            "id": "990c5c875eab0e33",
            "type": "leaf",
            "state": {
              "type": "outline",
              "state": {
                "file": "Statistics 110/독립 vs 조건부 독립.md"
              }
            }
          }
        ],
        "currentTab": 3
      }
    ],
    "direction": "horizontal",
    "width": 300
  },
  "left-ribbon": {
    "hiddenItems": {
      "switcher:퀵 스위처 열기": false,
      "graph:그래프 뷰 열기": false,
      "canvas:새 캔버스 만들기": false,
      "daily-notes:오늘의 데일리 노트 열기": false,
      "templates:템플릿 삽입": false,
      "command-palette:명령어 팔레트 열기": false
    }
  },
  "active": "0047a872449aeab3",
  "lastOpenFiles": [
    "Statistics 110/연속 분포(Continuous Distribution).md",
    "Statistics 110/강의 인덱스.md",
    "Statistics 110/정규분포(Normal Distribution).md",
    "Statistics 110/이산분포(Discrete Distribution).md",
    "Statistics 110/지수분포().md",
    "Statistics 110/확률 변수(Random Variables).md",
    "확률변수(Random Variables).md",
    "확률변수(Random Variables.md).md",
    "확률변수(Random Variables.md",
    "BERT/개념 정리.md",
    "BERT/Abstract 요약.md",
    "Statistics 110/기반 개념.md",
    "BERT",
    "Statistics 110/기하분포(Geometric Dstribution).md",
    "기하분포(Geometric Dstribution.md",
    "Statistics 110/조건부 확률(Conditional Probability).md",
    "Read Me.md",
    "Statistics 110/평균(Means, Expected Values).md",
    "선형대수/벡터.md",
    "Python/판다스(Pandas).md",
    "Python/넘파이(Numpy).md",
    "선형대수/선형대수학의 초석, 벡터.md",
    "Statistics 110/독립 vs 조건부 독립.md",
    "Statistics 110/Birthday Problem.md",
    "Statistics 110/확률의 정의.md",
    "PyTorch/Troubleshooting.md",
    "PyTorch/Multi-GPU 학습.md",
    "Statistics 110/images/9-1.png",
    "Statistics 110/images",
    "Statistics 110/무제 파일.canvas",
    "그래프 이미지",
    "무제 파일.canvas",
    "PyTorch",
    "Statistics 110",
    "선형대수",
    "Python"
  ]
}